odoo/addons/shopinvader_payment_manual/README.rst
odoo/addons/shopinvader_payment_manual/__init__.py
odoo/addons/shopinvader_payment_manual/__manifest__.py
odoo/addons/shopinvader_payment_manual/components/__init__.py
odoo/addons/shopinvader_payment_manual/components/payment_transaction_event_listerner.py
odoo/addons/shopinvader_payment_manual/demo/payment_demo.xml
odoo/addons/shopinvader_payment_manual/readme/CONTRIBUTORS.rst
odoo/addons/shopinvader_payment_manual/readme/DESCRIPTION.rst
odoo/addons/shopinvader_payment_manual/services/__init__.py
odoo/addons/shopinvader_payment_manual/services/payment_manual.py
odoo/addons/shopinvader_payment_manual/static/description/index.html
odoo12_addon_shopinvader_payment_manual-12.0.2.0.0.dist-info/METADATA
odoo12_addon_shopinvader_payment_manual-12.0.2.0.0.dist-info/WHEEL
odoo12_addon_shopinvader_payment_manual-12.0.2.0.0.dist-info/top_level.txt
odoo12_addon_shopinvader_payment_manual-12.0.2.0.0.dist-info/RECORD
