Metadata-Version: 2.1
Name: odoo12-addon-shopinvader-payment-manual
Version: 12.0.2.0.0
Summary: REST Services for manual payment (like bank transfer, check...)
Home-page: https://github.com/shopinvader/odoo-shopinvader-payment
Author: ACSONE SA/NV
License: AGPL-3
Platform: UNKNOWN
Classifier: Programming Language :: Python
Classifier: Framework :: Odoo
Classifier: License :: OSI Approved :: GNU Affero General Public License v3
Requires-Python: >=3.5
Requires-Dist: odoo12-addon-invader-payment-manual
Requires-Dist: odoo12-addon-shopinvader-payment
Requires-Dist: odoo (<12.1dev,>=12.0a)
